llama_index/memory/mem0/__init__.py
llama_index/memory/mem0/base.py
llama_index/memory/mem0/utils.py
llama_index_memory_mem0-1.0.0.dist-info/METADATA
llama_index_memory_mem0-1.0.0.dist-info/WHEEL
llama_index_memory_mem0-1.0.0.dist-info/licenses/LICENSE
llama_index_memory_mem0-1.0.0.dist-info/RECORD
