Metadata-Version: 2.4
Name: llama-index-memory-mem0
Version: 1.0.0
Summary: llama-index memory mem0 integration
Author-email: Your Name <you@example.com>
License-Expression: MIT
License-File: LICENSE
Requires-Python: <4.0,>=3.9
Requires-Dist: llama-index-core<0.15,>=0.13.0
Requires-Dist: mem0ai<2,>=1.0.0
